setup.py
cdb/__init__.py
cdb/cdb_web_service/__init__.py
cdb/cdb_web_service/api/__init__.py
cdb/cdb_web_service/api/fileSystemRestApi.py
cdb/cdb_web_service/api/itemRestApi.py
cdb/cdb_web_service/api/logRestApi.py
cdb/cdb_web_service/api/propertyRestApi.py
cdb/cdb_web_service/api/userRestApi.py
cdb/cdb_web_service/cli/__init__.py
cdb/cdb_web_service/cli/addItemLogEntryCli.py
cdb/cdb_web_service/cli/addItemPropertyValueCli.py
cdb/cdb_web_service/cli/addLogAttachmentCli.py
cdb/cdb_web_service/cli/addPropertyMetadataToPropertyValueCli.py
cdb/cdb_web_service/cli/cdbWebServiceCli.py
cdb/cdb_web_service/cli/cdbWebServiceSessionCli.py
cdb/cdb_web_service/cli/deleteItemPropertyValuesCli.py
cdb/cdb_web_service/cli/deleteLogCli.py
cdb/cdb_web_service/cli/getDirectoryListCli.py
cdb/cdb_web_service/cli/getItemCli.py
cdb/cdb_web_service/cli/getItemLogsCli.py
cdb/cdb_web_service/cli/getUserCli.py
cdb/cdb_web_service/cli/getUserGroupsCli.py
cdb/cdb_web_service/cli/getUsersCli.py
cdb/cdb_web_service/cli/loadLatticeDesignCli.py
cdb/cdb_web_service/cli/updateLogCli.py
cdb/cdb_web_service/cli/writeFileCli.py
cdb/common/__init__.py
cdb/common/api/__init__.py
cdb/common/api/cdbApi.py
cdb/common/api/cdbRestApi.py
cdb/common/cli/__init__.py
cdb/common/cli/cdbCli.py
cdb/common/cli/cdbDbCli.py
cdb/common/cli/cdbOptionParser.py
cdb/common/cli/cdbRestCli.py
cdb/common/cli/cdbRestSessionCli.py
cdb/common/client/__init__.py
cdb/common/client/cdbExceptionMapper.py
cdb/common/client/cdbHttpsConnection.py
cdb/common/client/cdbHttpsHandler.py
cdb/common/client/sessionManager.py
cdb/common/client/test.py
cdb/common/constants/__init__.py
cdb/common/constants/cdbHttpHeaders.py
cdb/common/constants/cdbHttpStatus.py
cdb/common/constants/cdbRole.py
cdb/common/constants/cdbServiceConstants.py
cdb/common/constants/cdbStatus.py
cdb/common/constants/itemDomain.py
cdb/common/exceptions/__init__.py
cdb/common/exceptions/authenticationError.py
cdb/common/exceptions/authorizationError.py
cdb_api.egg-info/PKG-INFO
cdb_api.egg-info/SOURCES.txt
cdb_api.egg-info/dependency_links.txt
cdb_api.egg-info/entry_points.txt
cdb_api.egg-info/top_level.txt