Metadata-Version: 1.0
Name: cdb-api
Version: 3.8.0
Summary: Python APIs used to communicate with Component Database
Home-page: https://github.com/AdvancedPhotonSource/ComponentDB
Author: Dariusz Jarosz
Author-email: djarosz@aps.anl.gov
License: Copyright (c) UChicago Argonne, LLC. All rights reserved.
Platform: UNKNOWN
